docker_watchdog/ConfigurationManager.py
docker_watchdog/Installation.py
docker_watchdog/Shutdown.py
docker_watchdog/Utility.py
docker_watchdog/Watchdog.py
docker_watchdog/__init__.py
docker_watchdog/__main__.py
docker_watchdog/main.py
docker_watchdog-0.0.5.dist-info/LICENSE
docker_watchdog-0.0.5.dist-info/METADATA
docker_watchdog-0.0.5.dist-info/WHEEL
docker_watchdog-0.0.5.dist-info/entry_points.txt
docker_watchdog-0.0.5.dist-info/top_level.txt
docker_watchdog-0.0.5.dist-info/zip-safe
docker_watchdog-0.0.5.dist-info/RECORD
