Metadata-Version: 2.1
Name: docker-watchdog
Version: 0.0.5
Summary: Service to perform automatic shutdown of idle container hosts
Home-page: http://github.com/adamrehn/docker-watchdog
Author: Adam Rehn
Author-email: adam@adamrehn.com
License: MIT
Keywords: docker continuous-integration
Platform: UNKNOWN
Classifier: License :: OSI Approved :: MIT License
Classifier: Programming Language :: Python :: 3.5
Classifier: Programming Language :: Python :: 3.6
Classifier: Programming Language :: Python :: 3.7
Classifier: Topic :: Software Development :: Build Tools
Classifier: Environment :: Console
Requires-Python: >=3.5
Requires-Dist: docker (>=3.0.0)
Requires-Dist: humanfriendly
Requires-Dist: requests
Requires-Dist: setuptools (>=38.6.0)
Requires-Dist: twine (>=1.11.0)
Requires-Dist: uptime
Requires-Dist: wheel (>=0.31.0)
